{"credentialSaved":true,"username":"tkhetib","courses":[{"name":"Admin Linux","cID":"244","id":"a8bc6"}],"files":{"a8bc6":[{"name":"EXAM-FISE.pdf","entryName":"EXAM","type":"Fichier","parent":null,"latest":true},{"name":"TDs-20250416.zip","entryName":"TDs","type":"Dossier","parent":null,"latest":true,"children":[{"name":"daemon.c","entryName":"daemon.c","type":"Fichier","courseID":"a8bc6","parent":"TDs-20250416","latest":false},{"name":"daemon2.c","entryName":"daemon2.c","type":"Fichier","courseID":"a8bc6","parent":"TDs-20250416","latest":false},{"name":"script-init-exemple","entryName":"script-init-exemple","type":"Fichier","courseID":"a8bc6","parent":"TDs-20250416","latest":false},{"name":"sujet-td1-2.pdf","entryName":"sujet-td1-2.pdf","type":"Fichier","courseID":"a8bc6","parent":"TDs-20250416","latest":false},{"name":"sujet-td3-4.pdf","entryName":"sujet-td3-4.pdf","type":"Fichier","courseID":"a8bc6","parent":"TDs-20250416","latest":false},{"name":"sujet-td5.pdf","entryName":"sujet-td5.pdf","type":"Fichier","courseID":"a8bc6","parent":"TDs-20250416","latest":false},{"name":"TP1-partie1.pdf","entryName":"TP1-partie1.pdf","type":"Fichier","courseID":"a8bc6","parent":"TDs-20250416","latest":false},{"name":"TP1-partie2.pdf","entryName":"TP1-partie2.pdf","type":"Fichier","courseID":"a8bc6","parent":"TDs-20250416","latest":false}]},{"name":"COURS-20250416.zip","entryName":"COURS","type":"Dossier","parent":null,"latest":true,"children":[{"name":"admin_unix.pdf","entryName":"admin_unix.pdf","type":"Fichier","courseID":"a8bc6","parent":"COURS-20250416","latest":false},{"name":"memento.pdf","entryName":"memento.pdf","type":"Fichier","courseID":"a8bc6","parent":"COURS-20250416","latest":false}]}]}}